Workbook

Sheet Sales Dashboard
B1: Monthly Sales Forecast Dashboard 2026 (Unconstrained Demand)
D2: SO at Mar 4th | E2: Feb actual + 10 months | G2: NBO sheet from CAE's CRM platform + Individual account progress + NPI | H2: Only what is put in the target need to be in the comment
B3: Salesperson | C3: (K$) Budget Target 2026 | D3: YTD+ SO | E3: (K$) Mar FCST 80% confidence | F3: (K$) GAP (Budget Target vs FCST) | G3: (K$) (3X GAP) Customer Opportunities 2026 | H3: Comments
B4: Intira | C4: 10578896 | D4: 8497618.6 | E4: =Intira!F18 -> 8869491.4 | F4: =E4-C4 -> -1709404.6 | G4: =Intira!H18 -> 114853.95 | H4: - AEG ID: focus on getting order of SIC73F1 * 20K pcs in Q4'26 ($65K). Budget is 2026 is 330K pcs (USD 1.226M). Due to market slow down and end customter still have stock of TI parts so we don't get volume order as planned. - Allflex: to maintian all SIC278 to be shipped out in 2026. Allflex wants to push out 1.5M units ($89K) from Dec'26 to Jan'27- maintain as budget - Received order from Caisley SIC279 * 460K pcs to be shipped out in 2026 with old price USD 0.21 (USD 96.6K) but pending for price discussion for low volume order
B5: Lisa | C5: 1924653.4 | D5: 1342050.7 | E5: =Lisa!D18 -> 1264422.1 | F5: =E5-C5 -> -660231.33 | G5: =Lisa!F18 -> 2378150 | H5: Closed new PO of SIC73F1 with Waferwon: 50K(done, HID/Sumida supply)+150Kpcs(need wait for HID pass qualification)
B6: Nuttapon | C6: 128557.24 | D6: 85997.496 | E6: =Nuttapon!D11 -> 115745.22 | F6: =E6-C6 -> -12812.016 | G6: =Nuttapon!F11 -> 455188.22 | H6: Order forecast of SIC73F1 from Hitachi JP (Jun., Sep., Dec., Mar.) at 6k to 9k units, totaling 24k to 36k units. ($110K)
B7: Shan | C7: 438365 | D7: 160033.35 | E7: =Shan!D12 -> 160593 | F7: =E7-C7 -> -277772 | G7: =Shan!F12 -> 832220 | H7: 4 products (SIC6149-91, SIC614A-AN, SIC6146-EG, SIC6146-6H with annual estimated use by customer at 50k, 600k, 90k, 300k) under qualification with post negotiation accepted pricing at 2.145, 2.2582, 1.95, 0.95/ unit. High (unlikely total volume is 1.04Million units ≈ 1.9MUSD). Realistic Consumption between 30-40% of total volume is 370K Units ≈ 680K USD)
B8: Terry | C8: 3536363 | D8: 2280953.2 | E8: =Terry!D21 -> 3245398 | F8: =E8-C8 -> -290964.98 | G8: =Terry!F21 -> 783400 | H8: - Chase for update status from Japanese customer for Astag RE41 passport reader for pre-production lot then first order timeline of RE41 will be more clear,60K pcs($39K) - FV will place another PO around 50 wafer($294K) for SIC5777 for the May and June Shipment
B9: Tunn | C9: 4630858.5 | D9: 3075470.7 | E9: =Tunn!D14 -> 4615139.5 | F9: =E9-C9 -> -15719 | G9: =Tunn!F14 -> 107600 | H9: Received PO for 1M ($230K) pcs 279 from APKID. Still waiting to hear back first week of March for TMV48 project.
B10: TOTAL | C10: 22000000 | D10: =SUM(D4:D9) -> 15442124 | E10: =SUM(E4:E9) -> 18270789 | F10: =E10-C10 -> -3729210.7 | G10: =SUM(G4:G9) -> 4671412.2
F11: Total (3X GAP) Unweighted | G11: =(F10*3)+G10 -> -6516220
B13: Total weighted FCST risk | E13: ='Risk & Opportunity'!H18 -> 886914.17
B14: Total weighted opportunities | E14: ='Risk & Opportunity'!T43 -> 1650907.7
B15: Total Overall Potential | E15: =E10-E13+E14 -> 19034783

Sheet Risk & Opportunity
E1: 0.7 | F1: High | N1: 0.7 | O1: High | P1: Remark: any opportunity with confidence level >=80% move to Revenue Forecast in the FOLLOWING month
E2: 0.5 | F2: Medium | N2: 0.5 | O2: Medium
A3: Risk/Issue against the Budget, and Support needed | E3: 0.1 | F3: Low | K3: Opportunities and Progress | N3: 0.1 | O3: Low
A4: Sales | B4: Customer | C4: Chip name | D4: Issue | E4: Support need | F4: Risk Level | G4: K$ Rev Impact | H4: K$ Weighted Rev | K4: Sales | L4: Customer | M4: Chip name | N4: P-code | O4: New Opportunity | P4: Confident Level | Q4: Volumes (Qty/pcs) | R4: Price/Unit | S4: K$ Unweighted Rev | T4: K$ Weighted Rev | U4: Expected Timeline 2026 | V4: Current Status | W4: Action item/ Support Need (Who/What/When)
A5: Nuttapon | B5: Techna | C5: SIC7150 | D5: Delivery lead time for SIC7150 is 7 months which is too long | E5: SC to shuffle production and pullin immediately | F5: Medium | G5: 57976.532 | H5: =IF(F5="Low",G5*$E$3, IF(F5="Medium",G5*$E$2, IF(F5="High",G5*$E$1,""))) -> 28988.266 | K5: Nuttapon | L5: KKP Bank | M5: Fido | O5: Fido card | P5: High | Q5: 20000 | R5: 10 | S5: =Table25[[#This Row],[Volumes (Qty/pcs)]]*Table25[[#This Row],[Price/Unit]] -> 200000 | T5: =IF(P5="Low",S5*$N$3, IF(P5="Medium",S5*$N$2, IF(P5="High",S5*$N$1,""))) -> 140000 | U5: Q2 | V5: Feb 20th: Review price structure and reseller agreement with IDEX, awaiting for IDEX reply Feb 17th: 1. Review and confirm IDEX reseller agreement by 20th Feb - PIC Nutt/ K.Marc 2. Create KKP proposal by 20th Feb - PIC Nutt/Karn
A6: Intira | B6: Allflex | C6: AFX | D6: AF+G1 CSP delivery schedule is delayed from originally planned | E6: Need SC to expedite with the supplier | F6: High | G6: =1600000*0.083 -> 132800 | H6: =IF(F6="Low",G6*$E$3, IF(F6="Medium",G6*$E$2, IF(F6="High",G6*$E$1,""))) -> 92960
A7: Lisa | B7: Waferwon | C7: SIC73F1 | D7: HID capacity insufficient | E7: HID supply lead time - Appripeya to get back on lead time -HID now fully loaded till end of Q3 -Waferwon rush on place new order 20K | F7: High | G7: 600000 | H7: =IF(F7="Low",G7*$E$3, IF(F7="Medium",G7*$E$2, IF(F7="High",G7*$E$1,""))) -> 420000 | K7: Intira | L7: Silca | M7: ATLF2SG2 | O7: OEM replacement | P7: Low | Q7: 100000 | R7: 1 | S7: =Table25[[#This Row],[Volumes (Qty/pcs)]]*Table25[[#This Row],[Price/Unit]] -> 100000 | T7: =IF(P7="Low",S7*$N$3, IF(P7="Medium",S7*$N$2, IF(P7="High",S7*$N$1,""))) -> 10000 | U7: Q3 | V7: Feb 17th: Customer to feedback sample result whether meet OEM requirment by 27th Mar - PIC Intira | W7: SA: Intira needs to verify if Silca needs any certificate for OEM, OEM cycle time - Silca will handle certificate, OEM will qualify for 12 months but Silca target to get the supply SC: Currently have stock on hand
A8: Terry | B8: SES | C8: SIC5777 | D8: Tariff impact lead to difficult to receive order from end customer | E8: None | F8: High | G8: =3500000*0.0797 -> 278950 | H8: =IF(F8="Low",G8*$E$3, IF(F8="Medium",G8*$E$2, IF(F8="High",G8*$E$1,""))) -> 195265 | K8: Shan | L8: Y-tex | M8: SIC379 | O8: Direct Chip Supply in cannister | P8: Low | Q8: 3000000 | R8: 0.2635 | S8: =Table25[[#This Row],[Volumes (Qty/pcs)]]*Table25[[#This Row],[Price/Unit]] -> 790500 | T8: =IF(P8="Low",S8*$N$3, IF(P8="Medium",S8*$N$2, IF(P8="High",S8*$N$1,""))) -> 79050 | U8: Q2 | V8: Feb 24th: Status: Say Q2 is more realistic for them to complete analyzing transition to Chip purchase while figuring out other factors with subcontractors. Purchase could start as late as Q1 2027, if not within 2026. | W8: SA: Shan to update the clear direction of Y-Tex getting the IC supply from SIC today H1 1.2M units SC: Product lead time for 3M/1.2M units?
A9: Terry | B9: Astag | C9: RE41 | D9: Pre-production delay due to customer need to add feature of reading at different transport data speed | E9: Support from CAE to help solve the issue for 43B type can be read in different trasnport speed None, due to we have help Astag on adding the speed feature and need to follow up Japanese end customer's confirmation for sending the pre-produciton lot | F9: Medium | G9: =60000*0.65 -> 39000 | H9: =IF(F9="Low",G9*$E$3, IF(F9="Medium",G9*$E$2, IF(F9="High",G9*$E$1,""))) -> 19500 | K9: Shan | L9: AnimalID BR | M9: SIC278 | O9: Direct Chip Supply in cannister | P9: Low | Q9: 1200000 | R9: 0.09713 | S9: =Table25[[#This Row],[Volumes (Qty/pcs)]]*Table25[[#This Row],[Price/Unit]] -> 116556 | T9: =IF(P9="Low",S9*$N$3, IF(P9="Medium",S9*$N$2, IF(P9="High",S9*$N$1,""))) -> 11655.6 | U9: Q3 | V9: Feb 24th: Status: considering the pricing and process to purchase chips directly from SIC. Still slient/ No feedback yet. | W9: SA: Shan to update the clear direction from Animal Brazil today
K10: Lisa | L10: D-Think | M10: 56NL | O10: Test new sample after holidays | P10: Medium | Q10: 240000 | R10: 0.055 | S10: =Table25[[#This Row],[Volumes (Qty/pcs)]]*Table25[[#This Row],[Price/Unit]] -> 13200 | T10: =IF(P10="Low",S10*$N$3, IF(P10="Medium",S10*$N$2, IF(P10="High",S10*$N$1,""))) -> 6600 | U10: Q4 | V10: Mar 5th: Will send new sample on Mar. Factory just started working, estimate will ship out on 18th- PIC Lisa
K11: Lisa | L11: Tatwah | M11: SIC379/278 Hitags256 | O11: Transition from 279 | P11: Low | Q11: 3000000 | R11: 0.21 | S11: =Table25[[#This Row],[Volumes (Qty/pcs)]]*Table25[[#This Row],[Price/Unit]] -> 630000 | T11: =IF(P11="Low",S11*$N$3, IF(P11="Medium",S11*$N$2, IF(P11="High",S11*$N$1,""))) -> 63000 | U11: Q4 | V11: Mar 5th: Cycle time for sample testing 1-2 months, to follow up test result by 20th Mar - PIC Lisa/Parada Check if 278 have German Waste Management Standard/Pigeon Race Standard--PIC CAE | W11: CAE: Complete new sample in qardant wafer 30K pcs SA: Lisa checked on customer cycle time for approval 1 month including field trial lead time. FYA: Special promotion price for qardant wafer or free sample PLM/PM: Prachanart to go to RFS gate
A12: Shan | B12: Tempocom | C12: SIC72A1 | D12: 1 Reel short for March delivery, awaiting customer rest of year forecast to be available in Feb, to add the reel into next delivery | E12: Verify new official MOQ, after 1st order lower yield/ wafer left Tempocom order under supplied by 1 reel (5K). Next order deadline by the 24th. If new order not issued, price goes up. | F12: Low | G12: 1059 | H12: =IF(F12="Low",G12*$E$3, IF(F12="Medium",G12*$E$2, IF(F12="High",G12*$E$1,""))) -> 105.9 | K12: Lisa | L12: Lanhai | M12: SIC7888 | O12: Close new PO on Q2 | P12: Medium | Q12: 2000000 | R12: 0.0522 | S12: =Table25[[#This Row],[Volumes (Qty/pcs)]]*Table25[[#This Row],[Price/Unit]] -> 104400 | T12: =IF(P12="Low",S12*$N$3, IF(P12="Medium",S12*$N$2, IF(P12="High",S12*$N$1,""))) -> 52200 | U12: Q2 | V12: Monitor the monthly shipment | W12: SA: Lisa checked on customer cycle time they will produce sample in Mar. then send out in Mar. for US, and EU customer for livestock customers for approval which will take 3-6months for field trial lead time, and MP schedule
K13: Lisa | L13: Lanhai | M13: SIC278 | O13: Close new PO on March | P13: Medium | Q13: 1000000 | R13: 0.056 | S13: =Table25[[#This Row],[Volumes (Qty/pcs)]]*Table25[[#This Row],[Price/Unit]] -> 56000 | T13: =IF(P13="Low",S13*$N$3, IF(P13="Medium",S13*$N$2, IF(P13="High",S13*$N$1,""))) -> 28000 | U13: Q1 | V13: Monitor the monthly shipment Mar. 5th Will ship 327Kpcs on 6th Mar., need another 10 wafers on April. -L/T 4 weeks
A14: Intira | B14: Caisley | C14: SIC279 | D14: Customer has issues with staffs shortage and the winding machine, therefore they have to change to buy the HDX coil with chip instead. In 2026, we put budget for 2M pcs to 287K pcs+ new PO 460K pcs (USD 415K --> USD 157K). Price for low volumn is under negotiation | E14: To support price for low volumn qty (order of 460K pcs) | F14: High | G14: =460000*0.21 -> 96600 | H14: =IF(F14="Low",G14*$E$3, IF(F14="Medium",G14*$E$2, IF(F14="High",G14*$E$1,""))) -> 67620
A15: Intira | B15: Sistema | C15: SIC278 | D15: Based on 3 months max rescheduling out, they would like to push out 1.5M pcs (USD 89K) from Oct'26 to Jan'27 | F15: High | G15: =1500000*0.0595 -> 89250 | H15: =IF(F15="Low",G15*$E$3, IF(F15="Medium",G15*$E$2, IF(F15="High",G15*$E$1,""))) -> 62475 | K15: Terry | L15: Freevision | M15: SIC57G5 | O15: Low-temp feature for pre-paid utility card | P15: Low | Q15: 3000000 | R15: 0.029 | S15: =Table25[[#This Row],[Volumes (Qty/pcs)]]*Table25[[#This Row],[Price/Unit]] -> 87000 | T15: =IF(P15="Low",S15*$N$3, IF(P15="Medium",S15*$N$2, IF(P15="High",S15*$N$1,""))) -> 8700 | U15: Q4 | V15: Feb 17th: Conclude comercial and feedback timeline to Winker - PIC Terry/Siriwan/Parada/Nutt/CCO/CEO
W16: SA: Terry to come up with business case by Feb 25th Overall is not possible to pull in because of the NPI timeline
K17: Terry | L17: Astag | M17: SIC73F1 | O17: IC+Plastic circular tag, Astag provide sample to end customer to validate the function | P17: Low | Q17: 2000 | R17: 2.5 | S17: =Table25[[#This Row],[Volumes (Qty/pcs)]]*Table25[[#This Row],[Price/Unit]] -> 5000 | T17: =IF(P17="Low",S17*$N$3, IF(P17="Medium",S17*$N$2, IF(P17="High",S17*$N$1,""))) -> 500 | U17: Q2 | V17: Feb 17th: Follow sample feedback after CNY by Mar 6th- PIC Terry Feb 25th: No feedback from customer, still evaluating
F18: TOTAL | G18: =SUM(Table2[K$ Rev Impact]) -> 1295635.5 | H18: =SUM(Table2[K$ Weighted Rev]) -> 886914.17 | K18: Terry | L18: IDAID | M18: SIC73F1 | O18: Vanguard: Potential of 6k pcs in Q2 | P18: Medium | Q18: 6000 | R18: 3.8585 | S18: =Table25[[#This Row],[Volumes (Qty/pcs)]]*Table25[[#This Row],[Price/Unit]] -> 23151 | T18: =IF(P18="Low",S18*$N$3, IF(P18="Medium",S18*$N$2, IF(P18="High",S18*$N$1,""))) -> 11575.5 | U18: Q2 | V18: Feb 17th: Follow up order after CNY by Mar 6th- PIC Terry
K20: Tunn | L20: APKID | M20: TMV48 | O20: DAF Truck OEM project | P20: Medium | Q20: 140000 | R20: 0.28 | S20: =Table25[[#This Row],[Volumes (Qty/pcs)]]*Table25[[#This Row],[Price/Unit]] -> 39200 | T20: =IF(P20="Low",S20*$N$3, IF(P20="Medium",S20*$N$2, IF(P20="High",S20*$N$1,""))) -> 19600 | U20: Q2 | V20: Feb 17th: To update progress after India business trip by Feb Mar 5th: Following up with the customer on their evaluation feedback. Will hear back from them by this month.
K21: Tunn | L21: Axess | M21: SIC56NL | O21: Ski card project. Trying to replace SLIX2 | P21: Low | Q21: 100000 | R21: 0.2 | S21: =Table25[[#This Row],[Volumes (Qty/pcs)]]*Table25[[#This Row],[Price/Unit]] -> 20000 | T21: =IF(P21="Low",S21*$N$3, IF(P21="Medium",S21*$N$2, IF(P21="High",S21*$N$1,""))) -> 2000 | U21: Q3 | V21: Feb 17th: Create Ski Card gen2 sample - PIC Rungnatha/ Prachanart Mar 5th: Follow up with the customer on their feedback on the evaluation report that we provided. Still need help from PLM and MEN to open a new project for this customer (SIC56NL ski card inlay)
K22: Tunn | L22: HID | M22: SIC7150 | O22: Currently, the customer is asking for MOQ and LT of this chip to add item in their system. The SC team provided the MOQ at 25 wafers (1M pcs) and LT w/o wafer at 10 months and LT w/ wafer at 5.5 months. Is there a way to reduce the LT? | P22: Low | Q22: 3000000 | R22: 0.0588 | S22: =Table25[[#This Row],[Volumes (Qty/pcs)]]*Table25[[#This Row],[Price/Unit]] -> 176400 | T22: =IF(P22="Low",S22*$N$3, IF(P22="Medium",S22*$N$2, IF(P22="High",S22*$N$1,""))) -> 17640 | U22: Q4 | V22: Feb 17th: HID feedback lower product performance than EM, SIC to get some sample from HID to test - PIC Tunn/ Parada Mar 5th: HID feedback that the price that we re-proposed is still not competitive. I have already asked the customer to suggest what would be competitive. In Following up mode. | W22: MEN: Rungnatha to create Ski Card gen2 sample before Songkarn 18th SA: Align with customer for new sample cycle time PLM: To release RFS gate for new product form factor by Apr 30th
K23: Tunn | L23: HID | M23: SIC56NL | O23: Trying to get project from HID | P23: Low | Q23: 5000000 | R23: 0.07351 | S23: =Table25[[#This Row],[Volumes (Qty/pcs)]]*Table25[[#This Row],[Price/Unit]] -> 367550 | T23: =IF(P23="Low",S23*$N$3, IF(P23="Medium",S23*$N$2, IF(P23="High",S23*$N$1,""))) -> 36755 | U23: Q4 | V23: Feb 17th: Reqest for counter proposal for price deduction by Feb 27th - PIC Tunn/ K.Marc Mar 5th: HID feedback that the price that we re-proposed is still not competitive. I have already asked the customer to suggest what would be competitive. In Following up mode. | W23: We cannot pull in because HID already place 1H order to competitor and we need to provide the test result based on HID's form factor
K24: Tunn | L24: HID | M24: SIC72A1 | O24: Trying to get project from HID | P24: Low | Q24: 3500000 | R24: 0.0875 | S24: =Table25[[#This Row],[Volumes (Qty/pcs)]]*Table25[[#This Row],[Price/Unit]] -> 306250 | T24: =IF(P24="Low",S24*$N$3, IF(P24="Medium",S24*$N$2, IF(P24="High",S24*$N$1,""))) -> 30625 | U24: Q4 | V24: Feb 17th: HID feedback on Feb 16th that there is no business urgent, current price from Atmel is satisfy will consider again -- Follow up need in Q2 - PIC Tunn Mar 5th: HID feedback that the price that we re-proposed is still not competitive. I have already asked the customer to suggest what would be competitive. In Following up mode. | W24: We cannot pull in because HID already place 1H order to competitor
K25: Tunn | L25: Omnia | M25: SIC7150 | O25: The leadtime from SC is very long (8 months). The reason that Omnia want to switch to us is because EM leadtime is too long (more than 12 weeks) | P25: Medium | Q25: 1000000 | R25: 0.08 | S25: =Table25[[#This Row],[Volumes (Qty/pcs)]]*Table25[[#This Row],[Price/Unit]] -> 80000 | T25: =IF(P25="Low",S25*$N$3, IF(P25="Medium",S25*$N$2, IF(P25="High",S25*$N$1,""))) -> 40000 | U25: Q4 | V25: Feb 17th: To update progress after India business trip by Feb 23th - PIC Tunn Feb 26: Still have no concrete plan for this chip. Will need to wait to hear the feedback from the customer side once we ship out the 120k pcs.
K26: Tunn | L26: Omnia | M26: SIC279 | O26: Close the rest of the PO for 2026 | P26: High | Q26: 400000 | R26: 0.2 | S26: =Table25[[#This Row],[Volumes (Qty/pcs)]]*Table25[[#This Row],[Price/Unit]] -> 80000 | T26: =IF(P26="Low",S26*$N$3, IF(P26="Medium",S26*$N$2, IF(P26="High",S26*$N$1,""))) -> 56000 | U26: Q3 | V26: Feb 17th: To update progress after India business trip by Feb Mar 5th: Still waiting for the feedback from the customer side. Will follow up with them constantly. | W26: Based on 8 months lead time there is no way to meet 1H
K27: Tunn | L27: BTG | M27: SIC379 | O27: Waiting for customer evaluation | P27: High | Q27: 11500 | R27: 0.2885 | S27: =Table25[[#This Row],[Volumes (Qty/pcs)]]*Table25[[#This Row],[Price/Unit]] -> 3317.75 | T27: =IF(P27="Low",S27*$N$3, IF(P27="Medium",S27*$N$2, IF(P27="High",S27*$N$1,""))) -> 2322.425 | U27: Q2 | V27: Feb 17th: Follow up sample evaluation result by Feb 27th - PIC Tunn/ CAE Feb 26: Customer will probably take only the MOQ of 11,500 pcs this year. Will fully transition next year. Will try to get them to order more this year.
K28: Tunn | L28: Escatec | M28: SIC279 | O28: Waiting for customer evaluation | P28: High | Q28: 11500 | R28: 0.3099 | S28: =Table25[[#This Row],[Volumes (Qty/pcs)]]*Table25[[#This Row],[Price/Unit]] -> 3563.85 | T28: =IF(P28="Low",S28*$N$3, IF(P28="Medium",S28*$N$2, IF(P28="High",S28*$N$1,""))) -> 2494.695 | U28: Q2 | V28: Feb 17th: Follow up sample evaluation result by Feb 27th - PIC Tunn/ CAE Feb 26: Assuming the same case with BTG will happen. Still have not heard back from the customer. Will keep following up with them.
K30: Tunn | L30: Wigidex | M30: SIC56NL | O30: Minibar project. We have received the PO from the customer, but still need to RFS the product. | P30: High | Q30: 140000 | R30: 0.1 | S30: =Table25[[#This Row],[Volumes (Qty/pcs)]]*Table25[[#This Row],[Price/Unit]] -> 14000 | T30: =IF(P30="Low",S30*$N$3, IF(P30="Medium",S30*$N$2, IF(P30="High",S30*$N$1,""))) -> 9800 | U30: Q2 - Q4 | V30: Feb 17th: Request Management support to decide doing trading busines model rather than creating new standard product by Feb 25th - PIC K.Marc Mar 5th: The customer can accept the first shipment as late as June 2026
K31: Shan | L31: IDOLOGY | M31: SIC479 | O31: What does each size cost in less than 10,000 and more than 10,000 quantities with our ICAR #? Per CAE Response --> We have SIC279 12mm glass tag but with limited qty. that we need to keep for Oregon project, SIC279 isn't recommend for new design. Product Availability (PCODE + Brochure) available for approx 6 months so seems there is a gap | P31: Low | Q31: 10000 | R31: 2.205 | S31: =Table25[[#This Row],[Volumes (Qty/pcs)]]*Table25[[#This Row],[Price/Unit]] -> 22050 | T31: =IF(P31="Low",S31*$N$3, IF(P31="Medium",S31*$N$2, IF(P31="High",S31*$N$1,""))) -> 2205 | U31: Q3 | V31: Feb 24th: Cant accept standard prices, too high for lower volume. Market retail price is $3.95. Following up for price expectation.
K33: Shan | L33: Key Craze | M33: ULTX | O33: Visting Bangkok on March 7th / Invited to SIC Awaiting confirmation. | P33: Low | Q33: 10000 | R33: 1.8 | S33: =Table25[[#This Row],[Volumes (Qty/pcs)]]*Table25[[#This Row],[Price/Unit]] -> 18000 | T33: =IF(P33="Low",S33*$N$3, IF(P33="Medium",S33*$N$2, IF(P33="High",S33*$N$1,""))) -> 1800 | U33: Q1 | V33: Feb 24th: Awaiting visit confirmation / visit objectives. Touch based, but no clear price exptation given, expressed interest in SILICA exclusive GTN (told can’t supply that)
K34: Shan | L34: Mepco | M34: SIC43NT/S1 | O34: No Formulated Technical Plan to support Label Makers in place, Create a Technical plan for label makers to adopt RF/ NFC into their existing processes | P34: Low | Q34: 500000 | R34: 0.2 | S34: =Table25[[#This Row],[Volumes (Qty/pcs)]]*Table25[[#This Row],[Price/Unit]] -> 100000 | T34: =IF(P34="Low",S34*$N$3, IF(P34="Medium",S34*$N$2, IF(P34="High",S34*$N$1,""))) -> 10000 | U34: Q4 | V34: Feb 24th: 70% UHF 30% NFC requirement. Discussed with Muehlbauer and conference call tonight. NDA with Muehlbauer inprogress. Muehlbaur claims to not push materials (Chip), but highly coupled with NXP. Engaged with Engineering to verify SIC NFC special commands compatibility with MB encore engineering.
K35: Shan | L35: STRATTEC | M35: ULTX | O35: Qualification outcomes TBA ULTX SIC6149-91 | P35: Medium | Q35: 50000 | R35: 2.145 | S35: =Table25[[#This Row],[Volumes (Qty/pcs)]]*Table25[[#This Row],[Price/Unit]] -> 107250 | T35: =IF(P35="Low",S35*$N$3, IF(P35="Medium",S35*$N$2, IF(P35="High",S35*$N$1,""))) -> 53625 | U35: Q1 | V35: Feb 24th: Given customer a harder stop to purchase plan, close this opportunity if no response within February.
K36: Shan | L36: STRATTEC | M36: ULTX | O36: Qualification outcomes TBA ULTX SIC614A-AN | P36: Medium | Q36: 600000 | R36: 2.2582 | S36: =Table25[[#This Row],[Volumes (Qty/pcs)]]*Table25[[#This Row],[Price/Unit]] -> 1354920 | T36: =IF(P36="Low",S36*$N$3, IF(P36="Medium",S36*$N$2, IF(P36="High",S36*$N$1,""))) -> 677460 | U36: Q1 | V36: Feb 24th: Given customer a harder stop to purchase plan, close this opportunity if no response within February.
K37: Shan | L37: STRATTEC | M37: ULTX | O37: Qualification outcomes TBA ULTX SIC6146-EG | P37: Medium | Q37: 90000 | R37: 1.95 | S37: =Table25[[#This Row],[Volumes (Qty/pcs)]]*Table25[[#This Row],[Price/Unit]] -> 175500 | T37: =IF(P37="Low",S37*$N$3, IF(P37="Medium",S37*$N$2, IF(P37="High",S37*$N$1,""))) -> 87750 | U37: Q1 | V37: Feb 24th: Given customer a harder stop to purchase plan, close this opportunity if no response within February.
K38: Shan | L38: STRATTEC | M38: THV46 | O38: Qualification outcomes TBA THV46 SIC6146-6H | P38: Medium | Q38: 300000 | R38: 0.95 | S38: =Table25[[#This Row],[Volumes (Qty/pcs)]]*Table25[[#This Row],[Price/Unit]] -> 285000 | T38: =IF(P38="Low",S38*$N$3, IF(P38="Medium",S38*$N$2, IF(P38="High",S38*$N$1,""))) -> 142500 | U38: Q1 | V38: Feb 24th: Given customer a harder stop to purchase plan, close this opportunity if no response within February.
K39: Terry | L39: E-Garde | M39: SIC618A | O39: LF+AES access control | P39: Medium | Q39: 200000 | R39: 1.7 | S39: =Table25[[#This Row],[Volumes (Qty/pcs)]]*Table25[[#This Row],[Price/Unit]] -> 340000 | T39: =IF(P39="Low",S39*$N$3, IF(P39="Medium",S39*$N$2, IF(P39="High",S39*$N$1,""))) -> 170000 | U39: Q1 | V39: Feb 17th: 1. Follow up Miwa feedback by 20th Feb - PIC: Terry/Parada Feb 25th: Miwa have successfully encode our chip to their lock, and confirm can be use now, currently we are gna help them develop the software to be implement into MP est. around 2 weeks for this support. After supporting the software then move forward to reliability test, E-garde will consider order 100 pcs for this.
K40: Terry | L40: SES | M40: SIC56ID | O40: Lundry tag | P40: Low | Q40: 3500000 | R40: 0.048 | S40: =Table25[[#This Row],[Volumes (Qty/pcs)]]*Table25[[#This Row],[Price/Unit]] -> 168000 | T40: =IF(P40="Low",S40*$N$3, IF(P40="Medium",S40*$N$2, IF(P40="High",S40*$N$1,""))) -> 16800 | U40: Q4 | V40: Feb 17th: Follow project feedback after CNY by Mar 6th- PIC Terry Feb 25th: No resposne from Rex on the project status
K41: Terry | L41: Monokoto | M41: RE31 | O41: NFC gaming device | P41: Low | Q41: 3000 | R41: 0.8315 | S41: =Table25[[#This Row],[Volumes (Qty/pcs)]]*Table25[[#This Row],[Price/Unit]] -> 2494.5 | T41: =IF(P41="Low",S41*$N$3, IF(P41="Medium",S41*$N$2, IF(P41="High",S41*$N$1,""))) -> 249.45 | U41: Q4 | V41: Feb 17th: To identify concete project and information from Monokoto by Mar 6th- PIC Terry Feb 25th: End customer conducted filed test in mid Jan for the prototype Monokoto have made, now discussing internally for formal project approval with the management
K42: Terry | L42: Hangyang | M42: SIC279/SIC379 | P42: Medium | Q42: 6000 | R42: 0.4 | S42: =Table25[[#This Row],[Volumes (Qty/pcs)]]*Table25[[#This Row],[Price/Unit]] -> 2400 | U42: Q1 | V42: Feb 27th: Request to buy 6K pcs of SIC279
Q43: TOTAL | S43: =SUBTOTAL(109,S6:S42) -> 5591703.1 | T43: =SUBTOTAL(109,T6:T42) -> 1650907.7

Sheet Sheet2
B3: Intira | C3: Fasthink | D3: ULTX | E3: New orders placed on 27th Feb and need on 23-Mar * 10K pcs and 1-Apr * 10K pcs. Currently SC confirms to ship out on 30th Apr. | F3: Expedite output on ULTX Wedge | G3: High | H3: =10000*1.15 -> 11500 | I3: =IF(G3="Low",H3*$E$3, IF(G3="Medium",H3*$E$2, IF(G3="High",H3*$E$1,""))) -> 0

Sheet Sheet1

Sheet Intira
B1: Weekly Sales Dashboard 2026 | E1: Remark: this must be linked to the Rolling Forcast file with SC team
B2: 2026 Budget | C2: As of 3-Feb | D2: As of 24-Feb | E2: Jan actual + 11 months | F2: Feb actual + 10 mths
B4: Budget Target | C4: Actual + Open SO | D4: Actual + Open SO | E4: Feb FCST 80% confidence | F4: Mar FCST 80% confidence | G4: (K$) GAP vs FCST | H4: (3X GAP) Customer Opportunities 2026 (K$) | I4: Sales Plan Comment
A5: Sales Person
A6: AEG ID | B6: 1231992.9 | C6: 0 | D6: =3220+170660 -> 173880 | E6: =(20000*3.2571) -> 65142 | F6: =D6+(20000*3.2571) -> 239022 | G6: =F6-B6 -> -992970.88 | H6: 0 | I6: Feb 1st: Focus on getting order of SIC73F1 Opportunity 1: Try to get SIC7150 (in budget)
A7: Allflex | B7: 7410711.1 | C7: =935387.94+6485398.87 -> 7420786.8 | D7: =935387.94+550440.86+6004563.005 -> 7490391.8 | E7: =C7-(1588420*0.083) -> 7288948 | F7: =D7-(1588420*0.083) -> 7358552.9 | G7: =F7-B7 -> -52158.125 | H7: 0 | I7: Need help on pull in AF+G1 CSP shipment and AF+G2 ramp up in 2026 Keep all SIC278 to be shipped out in 2026 (current they want to push out 1.5M pcs from 2026 to Jan'27)
A8: Caisley | B8: 415800 | C8: =60375+0 -> 60375 | D8: 60375 | E8: =(1000000*0.21)+C8 -> 270375 | F8: =D8+(460000*0.21) -> 156975 | G8: =F8-B8 -> -258825 | H8: 0 | I8: Due to staffs shortage and machine problem, they will need to buy coil+chips and can place PO for SIC279 * 460K pcs in 2026
A9: Fasthink | B9: 685064.81 | C9: =136658.55+188098.06 -> 324756.61 | D9: =81911.619+78130.3698+164714.6212 -> 324756.61 | E9: =C9+((180000*1.69)+(10000*1.24)+(3000*1.22))*1.109 -> 679924.95 | F9: =D9+((180000*1.69)+(10000*1.24)+(3000*1.22))*1.109 -> 679924.95 | G9: =F9-B9 -> -5139.864 | H9: =100000*1 -> 100000 | I9: Opportunity for ATLF2SG2 GT for OEM customer (not in budget)
A10: JMA | B10: 75799.799 | C10: =13570.74+126856.45+13272 -> 153699.19 | D10: =36298.8409+9047.162774+131404.6464 -> 176750.65 | E10: =C10 -> 153699.19 | F10: =D10 -> 176750.65 | G10: =F10-B10 -> 100950.85 | H10: 0
A11: Kaba ILCO | B11: 89594.12 | C11: =27000+72900 -> 99900 | D11: =19800+22800+57300 -> 99900 | E11: =C11+(4000*0.9)+(10000*1.56) -> 119100 | F11: =D11 -> 99900 | G11: =F11-B11 -> 10305.88 | H11: 0
A12: Minda Silca | B12: 4791.78 | C12: =4871.55+4871.55 -> 9743.1 | D12: =4871.549+4871.549 -> 9743.098 | E12: =C12 -> 9743.1 | F12: =D12 -> 9743.098 | G12: =F12-B12 -> 4951.318 | H12: =G12*3 -> 14853.954
A13: Smartrac | B13: 141920 | C13: =29710.8+91962+5170 -> 126842.8 | D13: =29710.8+26881.2+85430.8 -> 142022.8 | E13: =C13 -> 126842.8 | F13: =D13 -> 142022.8 | G13: =F13-B13 -> 102.8 | H13: 0
A14: Veridat | B14: 27381.6 | C14: 0 | D14: 0 | E14: =C14 -> 0 | F14: =D14 -> 0 | G14: =F14-B14 -> -27381.6 | H14: 0 | I14: Depends on water card samples availability
A15: Spark Minda | B15: 495840 | C15: =0+6600 -> 6600 | D15: 6600 | E15: =C15 -> 6600 | F15: =C15 -> 6600 | G15: =F15-B15 -> -489240 | H15: 0
A18: TOTAL | B18: =SUM(B6:B17) -> 10578896 | C18: =SUM(C6:C17) -> 8202703.5 | D18: =SUM(D6:D17) -> 8484420 | E18: =SUM(E6:E17) -> 8720375 | F18: =SUM(F6:F17) -> 8869491.4 | G18: =SUM(G6:G17) -> -1709404.6 | H18: =SUM(H6:H17) -> 114853.95
G19: Total (3X GAP) | H19: =(G18+H18)*3 -> -4783652

Sheet Lisa
B1: Weekly Sales Dashboard 2026
B2: 2026 Budget | C2: SOat endofJan | D2: Feb actual + 10 months
A4: Sales Person Lisa | B4: Budget Target | C4: SO | D4: Mar FCST 80% confidence | E4: GAP vs FCST (K$) | F4: (3X GAP) Customer Opportunities 2026 (K$) | G4: Sales Plan Comment
A5: Fofia | B5: 184000 | C5: 325335 | D5: =C5 -> 325335 | E5: =C5-D5 -> 0 | F5: 230000 | G5: Close 2H frame order --379: 1Mpcs
A6: Hawang | B6: 137114 | C6: 123665 | D6: =C6*0.8 -> 98932 | E6: =-(C6-D6) -> -24733
A7: Lanhai | B7: =47040+52400 -> 99440 | C7: 441125 | D7: =C7 -> 441125 | E7: =-(C7-D7) -> 0 | F7: 104400 | G7: Close 7888 PO on Q3: 2Mpcs
A8: Soartech | B8: =58472+297990+56720 -> 413182 | C8: 199327 | D8: =C8*0.8 -> 159461.6 | E8: =-(C8-D8) -> -39865.4
A9: Tonghua | B9: 132288 | C9: 1824 | D9: =C9 -> 1824 | E9: =-(C9-D9) -> 0 | F9: 62400 | G9: Close new PO on Q2: RA10-30Kpcs, RE31-100Kpcs
A10: Voraus | B10: 54000 | C10: 20020 | D10: =C10/2 -> 10010 | E10: =-(C10-D10) -> -10010 | F10: 11000 | G10: Close new PO on Q2:DST80 non-marking 20Kpcs
A11: Weferwon | B11: 179614 | C11: 325335 | D11: =C11*0.7 -> 227734.5 | E11: =-(C11-D11) -> -97600.5 | F11: 600000 | G11: Closed new PO: 50K(done, HID+Sumida supply)+150Kpcs(need wait for HID pass qualification)
A12: EEDENG | B12: 18000 | C12: / | D12: =C12 -> / | F12: 10350 | G12: To close new PO on Mar: 23000pcs
A13: HUALIN | B13: 13000 | C13: / | D13: =C13 -> / | F13: 60000 | G13: To promote 7888 again with better price: 1Mpcs
A14: Tatwah | B14: 25200 | C14: / | D14: =C14 -> / | F14: =1150000+150000 -> 1300000 | G14: US project:279 1-3Mpcs; 278 1-5Mpcs(30% chances)
A15: NBO
A16: NBO
A17: NBO
A18: TOTAL | C18: =SUM(C5:C14) -> 1436631 | D18: =SUM(D5:D14) -> 1264422.1 | E18: =SUM(E5:E14) -> -172208.9 | F18: =SUM(F5:F17) -> 2378150
E19: Total (3X GAP) | F19: =E18*3 -> -516626.7
G21: S

Sheet Nuttapon
B1: Weekly Sales Dashboard 2026
B2: 2026 Budget | C2: SO at Mar 4th | D2: Feb actual + 11 months
B4: Budget Target (K$) | C4: YTD+ SO (K$) | D4: Mar FCST 80% confidence (K$) | E4: GAP vs FCST (K$) | F4: (3X GAP) Customer Opportunities 2026 (K$) | G4: Sales Plan Comment
A5: Nuttapon customer
A6: Hitachi TH | B6: 27500 | C6: 0 | D6: 27500 | E6: =D6-B6 -> 0 | F6: 110000 | G6: Order forecast from Hitachi JP (Jun., Sep., Dec., Mar.) at 6k to 9k units, totaling 24k to 36k units. ($110K)
A7: Techna | B7: 98000 | C7: 85188.22 | D7: 85188.22 | E7: =D7-B7 -> -12811.78 | F7: =D7+60000 -> 145188.22 | G7: Deliver SIC7150 order 1M pcs in July or faster Close SIC278 for 1M units ($60K) by end of March 2026
A8: Head | B8: 3057 | C8: 0 | D8: =B8 -> 3057 | E8: =D8-B8 -> 0 | G8: Follow up repeat orders 1K pcs ($4.6K)
A9: KKP Bank | F9: 200000 | G9: Summarize price proposal and submit to KKP Bank by mid of Feb
A11: TOTAL | B11: 128557.24 | C11: =SUM(C6:C10) -> 85188.22 | D11: =SUM(D6:D10) -> 115745.22 | E11: =SUM(E6:E10) -> -12811.78 | F11: =SUM(F5:F10) -> 455188.22
E12: Total (3X GAP) | F12: =E11*3 -> -38435.339

Sheet Shan
B1: Weekly Sales Dashboard 2026
B2: 2026 Budget | C2: SO at end of Jan | D2: Feb actual + 11 months
B4: Budget Target (K$) | C4: SO | D4: Mar FCST 80% confidence | E4: GAP vs FCST (K$) | F4: (3X GAP) Customer Opportunities 2026 (K$) | G4: Sales Plan Comment
A5: Customer List
A6: IKS | B6: 116000 | C6: 132000 | D6: 132000 | E6: =C6-D6 -> 0 | F6: 0 | G6: AKS signed frame order has high confidence >90%.
A7: Tempocom | B7: 142965 | C7: 28593 | D7: 28593 | E7: =B7-D7 -> 114372 | F7: =E7 -> 114372 | G7: SIC72A1 product consumption was estimated by customer between 500K-1M units for year 1
A8: Strattec | B8: 174000 | C8: 0 | D8: 0 | E8: =B8-D8 -> 174000 | F8: 680553 | G8: 4 products (SIC6149-91, SIC614A-AN, SIC6146-EG, SIC6146-6H with annual estimated use by customer at 50k, 600k, 90k, 300k) under qualification with post negotiation accepted pricing at 2.145, 2.2582, 1.95, 0.95/ unit. High (unlikely total volume is 1.04Million units ≈ 1.9MUSD). Realistic Consumption between 30-40% of total volume is 370K Units ≈ 680K USD)
A9: TYKMA | B9: 5400 | C9: 0 | D9: 0 | E9: =B9-D9 -> 5400 | F9: 5000 | G9: Animal ID Encoder (Product) consumption was estimated by customer between 15 - 20 units for year 1
A10: Autentica | B10: 0 | C10: 0 | D10: 0 | E10: 0 | F10: 32295 | G10: SIC4340 equates to 25000 units consumed in 2026 compared to 100K they originally estimated
A12: TOTAL | B12: =SUM(B6:B11) -> 438365 | C12: =SUM(C6:C11) -> 160593 | D12: =SUM(D6:D11) -> 160593 | E12: =SUM(E6:E11) -> 293772 | F12: =SUM(F6:F11) -> 832220
E13: Total (3X GAP) | F13: =E12*3 -> 881316

Sheet Terry
B1: Weekly Sales Dashboard 2026
B2: 2026 Budget | C2: SO at end of Jan | D2: Feb actual + 10 months
A3: Customer (Terry) | B3: Budget Target (K$) | C3: SO | D3: March FCST 80% confidence | E3: GAP (Budget Target vs FCST) (K$) | F3: (3X GAP) Customer Opportunities 2026 (K$) | G3: Sales Plan Comment
A4: Changjo | B4: 277242 | C4: =992+24345 -> 25337 | D4: =67650+159000 -> 226650 | E4: =D4-B4 -> -50592 | G4: March 2nd : Received RA10 PO for 2026, 300k pcs($ 159K) Pending another 100K RA12 ($45.1K)
A5: Chilitag | B5: 14836 | D5: 13500 | E5: =D5-B5 -> -1336 | G5: March 2nd : Currently chasing RE31 PO form Chilitag team for April and May total 7K pcs( $5.25K)
A6: Duali | B6: 22100 | D6: =4000+20000 -> 24000 | E6: =D6-B6 -> 1900
A7: EPC | B7: 15434 | D7: =7717 -> 7717 | E7: =D7-B7 -> -7717 | G7: March 2nd : Currently chasing SIC73F1 PO for June 2k pcs ($7.7K)
A8: Freevision | B8: 1827510 | C8: =3585+44226+39420+1345143.298 -> 1432374.3 | D8: =1877652.82+29484+19710 -> 1926846.8 | E8: =D8-B8 -> 99336.82 | G8: Feb 2nd : Pending for SIC279 order 770K pcs ($ 150K) March 2nd : Announce that current PO for SIC5777 is only left around 3.7 million units, FV might need to place more SIC5777 for the shipment for May, June and July (Still need to wait for SIC57G5 confirmation) SIC278, FV want to know whether they are able to place MOQ 500k pcs at the price of $0.05497(Price for MOQ 3 million)
A9: Hitachi | B9: =85510 -> 85510 | C9: =35100+35100 -> 70200 | D9: =1045+95940 -> 96985 | E9: =D9-B9 -> 11475 | G9: March 2nd : Chase the rest of PO form Hitachi Thailand 40K($ 46.8k)
A10: Marshall | B10: 21129 | D10: 0 | E10: =D10-B10 -> -21129 | G10: March 2nd : Chase PO of SIC73F1 6K pcs in August ($21K)
A11: Queclink | B11: 784392 | C11: =60858+135240 -> 196098 | D11: =108642+686569.2 -> 795211.2 | E11: =D11-B11 -> 10819.2 | G11: Feb 2nd : Follow up for the commit order of 4.5 million pcs($882 K) in order to receive rebate price Rebate price: $0.1764, with 4.5 million pcs ($794K)
A12: SES | B12: 212002 | C12: =365.9718 -> 365.9718 | D12: 0 | E12: =D12-B12 -> -212002 | G12: Feb 2nd : Tariff issue lead to end customer profit have been eaten by tariff, demand still exist but hard to follow the order
A13: Willlink | B13: 121225 | C13: =10560+16320 -> 26880 | D13: 48686 | E13: =D13-B13 -> -72539 | G13: March 2nd : After Korea trip the confident of Willlink for RA12 have drop from 264Kpcs($121K) / year to 100K pcs ($49K) / year
A14: Goldsun | B14: 69453 | D14: 46302 | E14: =D14-B14 -> -23151 | G14: March 2nd : Winbond - Estimate start testing SIC73F1 around april UNC - Estimate start testing SIC73F1 around april
A15: E-Garde | B15: 59500 | D15: 59500 | E15: =D15-B15 -> 0 | F15: =150000*1.7 -> 255000 | G15: Feb 2nd : To help E-Garde to replace TI wedge to SIC wedge from MIWA est 150k pcs( $260k) March 2nd: Request support from EGD CEO to follow up on the SIC6146 order forecast. Miwa project is moving forawrd, however the order will come after Miwa have done the reliability test.
A16: Astag | B16: 26000 | D16: 0 | E16: =D16-B16 -> -26000 | G16: Feb 2nd : Still waiting for the RE41 passport reader response from end customer, currently no feedback from end customer side March 2nd: Pending final confirmation from end customer to ship out 500pcs of pre-production lot. Est. within next week
A17: Hanyang | F17: 56000 | G17: Feb 2nd : • Help to slove the impedence unstable issue for MP, SIC279 140k pcs(56k) • Potential of ASIC kick off if SIC are able to lower the NRE fee and put it into 12 years unit price (NRE $200K)
A18: CMSC | F18: 400000 | G18: Feb 2nd : • ASIC kick off for SIC73F1+SPI, NRE ($400K) Currently end customer are lack of Human resource for testing the new solution, project delay to end of 2026
A19: IDAID | F19: 70000 | G19: Feb 2nd : Chasing the new oppourtunity of 20K pcs of SIC73F1 to Vanguard( $70K)
A20: Hanyang | F20: =6000*0.4 -> 2400 | G20: March 2nd: Request 6K pcs of SIC279 ($2.4k)
A21: TOTAL | B21: =SUM(B4:B16) -> 3536333 | C21: =SUM(C4:C9) -> 1527911.3 | D21: =SUM(D4:D16) -> 3245398 | E21: =B21-D21 -> 290934.98 | F21: =SUM(F4:F20) -> 783400
E22: Total (3X GAP) | F22: =E21*3 -> 872804.94

Sheet Tunn
B1: Weekly Sales Dashboard 2026
B2: 2026 Budget | C2: SO at end of Jan | D2: Jan actual + 11 months
A4: TUNN | B4: Budget Target | C4: SO | D4: Feb FCST 80% confidence | E4: ($) GAP vs FCST | F4: (3X GAP) Customer Opportunities 2026 ($) | G4: Sales Plan Comment
A5: APK | B5: 183200 | D5: 224900 | E5: =D5-B5 -> 41700 | G5: Tentative on 1M pcs 279 project and TMV48 project Feb 26: Got PO for 1M pcs 279. Still waiting to hear back first week of March for TMV48 project.
A6: BTG | B6: 43275 | D6: 3675 | E6: =D6-B6 -> -39600 | G6: Feb 26: Customer feedback that they will buy MOQ for this year for the full transitioning next year.
A7: Elektronika | B7: 33600 | D7: 8700 | E7: =D7-B7 -> -24900 | F7: 33600 | G7: Access control and LF customer meeting in India
A8: Escatec | B8: 28850 | C8: 350 | D8: 3675 | E8: =D8-B8 -> -25175 | G8: Feb 26: Have not heard back from customer but assume the same with BTG.
A9: HID | B9: 3610270 | C9: 968424 | D9: =3702963.5+29120 -> 3732083.5 | E9: =D9-B9 -> 121813.5
A10: LUX | B10: 299916 | C10: 226980 | D10: 254916 | E10: =D10-B10 -> -45000 | F10: =500000*0.058+45000 -> 74000 | G10: Trying to close the Thai driver license project + SIC43NT project
A11: Omnia | B11: 157578 | C11: 24000 | D11: 167940 | E11: =D11-B11 -> 10362 | G11: Several ongoing project including SIC72A1, SIC7150, and SIC56NL Feb 26: Got PO for SIC56NL 560,000 pcs. Trying to work on SIC7150 project.
A12: Oregon | B12: 273244 | C12: 5508 | D12: 219250 | E12: =D12-B12 -> -53994 | G12: To be discussed in details with the customer again on yearly PO Feb 26: Customer is having a lot of inventory currently. They agree to take 38k pcs more 32mm GT later in the year and also the RW wedge for 50k pcs
A14: TOTAL | B14: =SUM(B5:B13) -> 4629933 | C14: =SUM(C5:C13) -> 1225262 | D14: =SUM(D5:D13) -> 4615139.5 | E14: =SUM(E5:E13) -> -14793.5 | F14: =SUM(F5:F13) -> 107600
E15: Total (3X GAP) | F15: =E14*3 -> -44380.5
